AUTHORS.rst
HISTORY.rst
LICENSE
MANIFEST.in
README.rst
setup.py
epiclient/__init__.py
epiclient/cli.py
epiclient/epiclient.py
epiclient/generate_json_input.py
epiclient.egg-info/PKG-INFO
epiclient.egg-info/SOURCES.txt
epiclient.egg-info/dependency_links.txt
epiclient.egg-info/entry_points.txt
epiclient.egg-info/not-zip-safe
epiclient.egg-info/requires.txt
epiclient.egg-info/top_level.txt
epiclient/json_schema/role_settings_schema.json
tests/__init__.py
tests/conftest.py
tests/test_epiclient.py
tests/json/formatted_sample_layout_live.json
tests/json/primary_sample_ca_settings.json
tests/json/sample_layout_live.json
tests/json/sample_layout_pn.json
tests/json/sample_layout_pr.json
tests/json/sample_sysinfo.json