Metadata-Version: 1.1
Name: epiclient
Version: 0.1.3
Summary: dce client for epipearl
Home-page: https://github.com/harvard-dce/epiclient
Author: nmaekawa
Author-email: nmaekawa@g.harvard.edu
License: Apache Software License 2.0
Keywords: epiclient
Platform: UNKNOWN
Classifier: Development Status :: 2 - Pre-Alpha
Classifier: Intended Audience :: Developers
Classifier: License :: OSI Approved :: Apache Software License
Classifier: Natural Language :: English
Classifier: Programming Language :: Python :: 2
Classifier: Programming Language :: Python :: 2.6
Classifier: Programming Language :: Python :: 2.7
